py_quarry-2.0.9.dist-info/licenses/LICENSE
quarry/__init__.py
quarry/__main__.py
quarry/core.py
quarry/foreman.py
quarry/inspector.py
quarry/miner.py
quarry/quarry.py
quarry/state.py
quarry/connectors/__init__.py
quarry/connectors/base.py
quarry/connectors/custom.py
quarry/connectors/fda.py
quarry/connectors/generic.py
quarry/connectors/nws.py
quarry/framework_profiles/__init__.py
quarry/framework_profiles/base.py
quarry/framework_profiles/cms/__init__.py
quarry/framework_profiles/cms/drupal.py
quarry/framework_profiles/cms/wordpress.py
quarry/framework_profiles/css/__init__.py
quarry/framework_profiles/css/bootstrap.py
quarry/framework_profiles/css/tailwind.py
quarry/framework_profiles/ecommerce/__init__.py
quarry/framework_profiles/ecommerce/shopify.py
quarry/framework_profiles/ecommerce/woocommerce.py
quarry/framework_profiles/frameworks/__init__.py
quarry/framework_profiles/frameworks/django.py
quarry/framework_profiles/frameworks/nextjs.py
quarry/framework_profiles/frameworks/react.py
quarry/framework_profiles/frameworks/vue.py
quarry/framework_profiles/universal/__init__.py
quarry/framework_profiles/universal/opengraph.py
quarry/framework_profiles/universal/schema_org.py
quarry/framework_profiles/universal/twitter_cards.py
quarry/lib/__init__.py
quarry/lib/bs4_utils.py
quarry/lib/http.py
quarry/lib/logging.py
quarry/lib/paths.py
quarry/lib/policy.py
quarry/lib/prompts.py
quarry/lib/ratelimit.py
quarry/lib/robots.py
quarry/lib/schemas.py
quarry/lib/selectors.py
quarry/lib/session.py
quarry/lib/theme.py
quarry/sinks/__init__.py
quarry/sinks/base.py
quarry/sinks/csv.py
quarry/sinks/jsonl.py
quarry/sinks/parquet.py
quarry/sinks/postgres.py
quarry/tools/excavate/__init__.py
quarry/tools/excavate/cli.py
quarry/tools/excavate/executor.py
quarry/tools/excavate/parser.py
quarry/tools/polish/__init__.py
quarry/tools/polish/cli.py
quarry/tools/polish/deduplicator.py
quarry/tools/polish/processor.py
quarry/tools/polish/transformers.py
quarry/tools/polish/validators.py
quarry/tools/scout/__init__.py
py_quarry-2.0.9.dist-info/METADATA
py_quarry-2.0.9.dist-info/WHEEL
py_quarry-2.0.9.dist-info/entry_points.txt
py_quarry-2.0.9.dist-info/top_level.txt
py_quarry-2.0.9.dist-info/RECORD
