Metadata-Version: 2.4
Name: py-quarry
Version: 2.0.9
Summary: An intuitive web scraping toolkit with intelligent templates and interactive workflows
Author: Russell Bomer
License: MIT
Project-URL: Homepage, https://github.com/russellbomer/quarry
Project-URL: Repository, https://github.com/russellbomer/quarry
Project-URL: Documentation, https://github.com/russellbomer/quarry#readme
Project-URL: Issues, https://github.com/russellbomer/quarry/issues
Keywords: web-scraping,data-extraction,html-parsing,css-selectors,react,vue,beautifulsoup,cli
Classifier: Development Status :: 4 - Beta
Classifier: Environment :: Console
Classifier: Intended Audience :: Developers
Classifier: Intended Audience :: Science/Research
Classifier: License :: OSI Approved :: MIT License
Classifier: Operating System :: OS Independent
Classifier: Programming Language :: Python :: 3
Classifier: Programming Language :: Python :: 3.10
Classifier: Programming Language :: Python :: 3.11
Classifier: Programming Language :: Python :: 3.12
Classifier: Programming Language :: Python :: 3.13
Classifier: Topic :: Internet :: WWW/HTTP :: Indexing/Search
Classifier: Topic :: Software Development :: Libraries :: Python Modules
Classifier: Topic :: Text Processing :: Markup :: HTML
Classifier: Typing :: Typed
Requires-Python: >=3.10
License-File: LICENSE
Requires-Dist: requests
Requires-Dist: beautifulsoup4
Requires-Dist: pandas
Requires-Dist: pyarrow
Requires-Dist: pyyaml
Requires-Dist: typer
Requires-Dist: questionary
Requires-Dist: pydantic
Requires-Dist: rich
Requires-Dist: click
Dynamic: license-file
